task_distribute/__init__.py
task_distribute/locker.py
task_distribute/test_locker.py
task_distribute/test_sacred.py
task_distribute-0.1.11.dist-info/METADATA
task_distribute-0.1.11.dist-info/WHEEL
task_distribute-0.1.11.dist-info/top_level.txt
task_distribute-0.1.11.dist-info/RECORD
